pycooldown/__init__.py
pycooldown/__main__.py
pycooldown/fixed_mapping.py
pycooldown/flexible_mapping.py
pycooldown/py.typed
pycooldown/sliding_window.py
pycooldown-0.1.0b11.dist-info/LICENSE
pycooldown-0.1.0b11.dist-info/WHEEL
pycooldown-0.1.0b11.dist-info/METADATA
pycooldown-0.1.0b11.dist-info/RECORD
